ynabsplitbudget/__init__.py
ynabsplitbudget/__main__.py
ynabsplitbudget/adjusters.py
ynabsplitbudget/client.py
ynabsplitbudget/models/__init__.py
ynabsplitbudget/models/account.py
ynabsplitbudget/models/category.py
ynabsplitbudget/models/exception.py
ynabsplitbudget/models/transaction.py
ynabsplitbudget/models/user.py
ynabsplitbudget/splitparser.py
ynabsplitbudget/syncrepository.py
ynabsplitbudget/transactionbuilder.py
ynabsplitbudget/ynabsplitbudget.py
ynab_split_budget-2.1.0.dist-info/LICENSE
ynab_split_budget-2.1.0.dist-info/METADATA
ynab_split_budget-2.1.0.dist-info/WHEEL
ynab_split_budget-2.1.0.dist-info/RECORD
