Metadata-Version: 2.3
Name: ynab-split-budget
Version: 2.1.0
Summary: Library to split and share You Need A Budget (YNAB) transactions between two budgets
License: MIT
Author: Daniel Basta
Author-email: ynab@basta.info
Requires-Python: >=3.8,<4.0
Classifier: License :: OSI Approved :: MIT License
Classifier: Operating System :: OS Independent
Classifier: Programming Language :: Python :: 3
Classifier: Programming Language :: Python :: 3.8
Classifier: Programming Language :: Python :: 3.9
Classifier: Programming Language :: Python :: 3.10
Classifier: Programming Language :: Python :: 3.11
Classifier: Programming Language :: Python :: 3.12
Classifier: Programming Language :: Python :: 3.13
Requires-Dist: pyyaml (>=6.0,<7.0)
Requires-Dist: requests (>=2.28,<3.0)
Requires-Dist: ynab-transaction-adjuster (>=2.0.0,<3.0.0)
